Metadata-Version: 2.1
Name: StringFuncs
Version: 0.0.3.217
Summary: A package for string manipulation, has 
Home-page: https://github.com/SamuelMorrisProjects/StringFuncs
Author: Samuel Morris
Author-email: samuelmorris333221@gmail.com
License: MIT
License-File: LICENSE.txt
